hhtrade/__init__.py
hhtrade/hhtrade.py
hhtrade-3.7.dist-info/METADATA
hhtrade-3.7.dist-info/WHEEL
hhtrade-3.7.dist-info/top_level.txt
hhtrade-3.7.dist-info/RECORD
