Metadata-Version: 2.2
Name: hhtrade
Version: 3.7
Summary: sqllib
Home-page: https://your.project.url
Author: hh
Author-email: hehuang0717@outlook.com
Classifier: Programming Language :: Python :: 3
Classifier: License :: OSI Approved :: MIT License
Classifier: Operating System :: OS Independent
Requires-Python: >=3.9
Requires-Dist: tqsdk==3.7.6
Requires-Dist: requests==2.28.1
Requires-Dist: texttable==1.7.0
Dynamic: author
Dynamic: author-email
Dynamic: classifier
Dynamic: description
Dynamic: description-content-type
Dynamic: home-page
Dynamic: requires-dist
Dynamic: requires-python
Dynamic: summary
